rinse/__init__.py
rinse/cookies/__init__.py
rinse/cookies/init/cookiecutter.json
rinse/cookies/init/{{cookiecutter.rinse_init_dir}}/bin/.gitkeep
rinse/cookies/init/{{cookiecutter.rinse_init_dir}}/lib/cran/.gitkeep
rinse/cookies/init/{{cookiecutter.rinse_init_dir}}/src/cran/.gitkeep
rinse/cookies/init/{{cookiecutter.rinse_init_dir}}/tmp/.gitkeep
rinse/core.py
rinse/rinse.py
rinse/utils.py
rinstall-0.2.3.dist-info/entry_points.txt
rinstall-0.2.3.dist-info/LICENSE
rinstall-0.2.3.dist-info/WHEEL
rinstall-0.2.3.dist-info/METADATA
rinstall-0.2.3.dist-info/RECORD
