Metadata-Version: 2.1
Name: rinstall
Version: 0.2.3
Summary: A configurable installer CLI for installing R from source (sudo and non-sudo).
Home-page: https://github.com/datasnakes/rinse
License: MIT
Keywords: r,installation
Author: Rob Gilmore
Author-email: robgilmore127@gmail.com
Requires-Python: >=3.4
Classifier: Development Status :: 4 - Beta
Classifier: Intended Audience :: Developers
Classifier: Intended Audience :: Education
Classifier: Intended Audience :: Science/Research
Classifier: Intended Audience :: System Administrators
Classifier: License :: OSI Approved :: MIT License
Classifier: Natural Language :: English
Classifier: Operating System :: POSIX :: Linux
Classifier: Operating System :: Unix
Classifier: Programming Language :: Other
Classifier: Programming Language :: Python :: 3
Classifier: Programming Language :: Python :: 3.4
Classifier: Programming Language :: Python :: 3.5
Classifier: Programming Language :: Python :: 3.6
Classifier: Programming Language :: Python :: 3.7
Classifier: Topic :: Scientific/Engineering
Classifier: Topic :: Software Development :: Libraries
Classifier: Topic :: System :: Filesystems
Requires-Dist: click (>=7.0,<8.0)
Requires-Dist: cookiecutter (>=1.6,<2.0)
Project-URL: Repository, https://github.com/datasnakes/rinse
